com/__init__.py
com/arg/__init__.py
com/arg/sql/__init__.py
com/arg/sql/utility/__init__.py
com/arg/sql/utility/sql3liteutility.py
arg.sqlutility-1.0.dist-info/LICENSE
arg.sqlutility-1.0.dist-info/METADATA
arg.sqlutility-1.0.dist-info/WHEEL
arg.sqlutility-1.0.dist-info/top_level.txt
arg.sqlutility-1.0.dist-info/RECORD
